nextcordwavelink/__init__.py
nextcordwavelink/__main__.py
nextcordwavelink/backoff.py
nextcordwavelink/enums.py
nextcordwavelink/exceptions.py
nextcordwavelink/filters.py
nextcordwavelink/lfu.py
nextcordwavelink/node.py
nextcordwavelink/payloads.py
nextcordwavelink/player.py
nextcordwavelink/py.typed
nextcordwavelink/queue.py
nextcordwavelink/tracks.py
nextcordwavelink/utils.py
nextcordwavelink/websocket.py
nextcordwavelink/types/__init__.py
nextcordwavelink/types/filters.py
nextcordwavelink/types/request.py
nextcordwavelink/types/response.py
nextcordwavelink/types/state.py
nextcordwavelink/types/stats.py
nextcordwavelink/types/tracks.py
nextcordwavelink/types/websocket.py
nextcordwavelink-3.5.0.dist-info/LICENSE
nextcordwavelink-3.5.0.dist-info/METADATA
nextcordwavelink-3.5.0.dist-info/WHEEL
nextcordwavelink-3.5.0.dist-info/top_level.txt
nextcordwavelink-3.5.0.dist-info/RECORD
